flink_mcp/__init__.py
flink_mcp/flink_mcp_server.py
flink_mcp/flink_sql_gateway_client.py
flink_mcp/main.py
flink_mcp/py.typed
flink_mcp-0.2.6.dist-info/METADATA
flink_mcp-0.2.6.dist-info/WHEEL
flink_mcp-0.2.6.dist-info/entry_points.txt
flink_mcp-0.2.6.dist-info/top_level.txt
flink_mcp-0.2.6.dist-info/RECORD
