Metadata-Version: 2.4
Name: flink-mcp
Version: 0.2.6
Summary: MCP server for Apache Flink SQL Gateway
Author-email: Maciek Brynski <maciej.brynski@cledar.com>
License: Apache-2.0
Project-URL: Homepage, https://github.com/cledar/flink-mcp
Project-URL: Issues, https://github.com/cledar/flink-mcp/issues
Project-URL: Repository, https://github.com/cledar/flink-mcp
Classifier: Intended Audience :: Developers
Classifier: License :: OSI Approved :: Apache Software License
Classifier: Operating System :: OS Independent
Classifier: Programming Language :: Python :: 3
Classifier: Programming Language :: Python :: 3 :: Only
Classifier: Programming Language :: Python :: 3.12
Classifier: Topic :: Software Development :: Libraries :: Python Modules
Requires-Python: >=3.12
Requires-Dist: fastmcp>=2.12.0
Requires-Dist: httpx>=0.27
Requires-Dist: python-dotenv>=1.0
Provides-Extra: dev
Requires-Dist: pytest>=8.0; extra == "dev"
Requires-Dist: pytest-asyncio>=0.23.0; extra == "dev"
Requires-Dist: ruff>=0.5.0; extra == "dev"
